{
  "version": 3,
  "middleware": {
    "/": {
      "files": [
        "server/edge-runtime-webpack.js",
        "server/src/middleware.js"
      ],
      "name": "src/middleware",
      "page": "/",
      "matchers": [
        {
          "regexp": "^(?:\\/(_next\\/data\\/[^/]{1,}))?(?:\\/((?!api\\/|_next\\/|_static\\/|_vercel|[\\w-]+\\.\\w+).*))(.json)?[\\/#\\?]?$",
          "originalSource": "/((?!api/|_next/|_static/|_vercel|[\\w-]+\\.\\w+).*)"
        }
      ],
      "wasm": [],
      "assets": [],
      "env": {
        "__NEXT_BUILD_ID": "FQtP8lfAly1EErq1TYE1K",
        "NEXT_SERVER_ACTIONS_ENCRYPTION_KEY": "IgyIA5V8HRE9eIL6EWflTiFJ7w7cuxH78KVS3ti2/gM=",
        "__NEXT_PREVIEW_MODE_ID": "519a7ed78897d9ab3bad9b69e389a9db",
        "__NEXT_PREVIEW_MODE_ENCRYPTION_KEY": "bcd5d99ed4622e32b3d6e76847305845132558ef7b3f8e5dad6f56d16e68344a",
        "__NEXT_PREVIEW_MODE_SIGNING_KEY": "7a5917b13f14fa7fadad5750cde04c8753a8d79de42d485b5fa01ff39fc11901"
      }
    }
  },
  "functions": {},
  "sortedMiddleware": [
    "/"
  ]
}