{
  "version": 3,
  "middleware": {
    "/": {
      "files": [
        "server/edge-runtime-webpack.js",
        "server/src/middleware.js"
      ],
      "name": "src/middleware",
      "page": "/",
      "matchers": [
        {
          "regexp": "^(?:\\/(_next\\/data\\/[^/]{1,}))?(?:\\/((?!api\\/|_next\\/|_static\\/|_vercel|[\\w-]+\\.\\w+).*))(.json)?[\\/#\\?]?$",
          "originalSource": "/((?!api/|_next/|_static/|_vercel|[\\w-]+\\.\\w+).*)"
        }
      ],
      "wasm": [],
      "assets": [],
      "env": {
        "__NEXT_BUILD_ID": "hqxbOc3wt5uGtPGxn-kfY",
        "NEXT_SERVER_ACTIONS_ENCRYPTION_KEY": "2OH55YSrVhNiRcVhDIDLn7qJROiKyRL1Ib+A9NEgRvo=",
        "__NEXT_PREVIEW_MODE_ID": "949bece4f9e098bc56b2c4c7c7bed1fc",
        "__NEXT_PREVIEW_MODE_ENCRYPTION_KEY": "264305a52e13048a8100a033cda3634d2c58ec1dda18a2b527e504988d0471f5",
        "__NEXT_PREVIEW_MODE_SIGNING_KEY": "054e58b615b167f9773f563d99961e3617e99a576fc1a58d2980088c855682b0"
      }
    }
  },
  "functions": {},
  "sortedMiddleware": [
    "/"
  ]
}